gondolin/__init__.py
gondolin/config_validator.py
gondolin/module_builder.py
gondolin/registry.py
gondolin/safe_proxy.py
gondolin-0.1.1.dist-info/METADATA
gondolin-0.1.1.dist-info/WHEEL
gondolin-0.1.1.dist-info/top_level.txt
gondolin-0.1.1.dist-info/RECORD
