Metadata-Version: 2.4
Name: gondolin
Version: 0.1.1
Summary: Policy-as-Code for AI Agents. Secure your LLM's access to tools with decorators and safe proxies.
Author-email: Jashua Gupta <findjashua@gmail.com>
Project-URL: Homepage, https://github.com/findjashua/gondolin
Classifier: Programming Language :: Python :: 3
Classifier: License :: OSI Approved :: MIT License
Classifier: Operating System :: OS Independent
Classifier: Topic :: Security
Classifier: Topic :: Software Development :: Libraries :: Python Modules
Requires-Python: >=3.9
Requires-Dist: PyYAML>=6.0
